django_yunpian/__init__.py
django_yunpian/admin.py
django_yunpian/apps.py
django_yunpian/exceptions.py
django_yunpian/models.py
django_yunpian/tests.py
django_yunpian/views.py
django_yunpian/migrations/0001_initial.py
django_yunpian/migrations/0002_auto_20190823_1746.py
django_yunpian/migrations/0003_auto_20190823_1900.py
django_yunpian/migrations/0004_auto_20190823_1939.py
django_yunpian/migrations/0005_template_min_interval_alter_account_id_and_more.py
django_yunpian/migrations/__init__.py
django_yunpian_app-1.1.0.dist-info/LICENSE
django_yunpian_app-1.1.0.dist-info/METADATA
django_yunpian_app-1.1.0.dist-info/WHEEL
django_yunpian_app-1.1.0.dist-info/top_level.txt
django_yunpian_app-1.1.0.dist-info/RECORD
