Metadata-Version: 2.1
Name: django-yunpian-app
Version: 1.1.0
Summary: 用于云片网的django app
Home-page: https://github.com/ramwin/django-yunpian-app
Author: Xiang Wang
Author-email: ramwin@qq.com
Classifier: Programming Language :: Python :: 3
Classifier: License :: OSI Approved :: MIT License
Classifier: Operating System :: OS Independent
License-File: LICENSE
Requires-Dist: yunpian-python-sdkdjangorestframework
